odoo/addons/purchase_force_invoiced/README.rst
odoo/addons/purchase_force_invoiced/__init__.py
odoo/addons/purchase_force_invoiced/__manifest__.py
odoo/addons/purchase_force_invoiced/i18n/es.po
odoo/addons/purchase_force_invoiced/i18n/fr.po
odoo/addons/purchase_force_invoiced/i18n/it.po
odoo/addons/purchase_force_invoiced/i18n/pt_BR.po
odoo/addons/purchase_force_invoiced/i18n/purchase_force_invoiced.pot
odoo/addons/purchase_force_invoiced/i18n/zh_CN.po
odoo/addons/purchase_force_invoiced/migrations/16.0.1.0.0/post-migrate.py
odoo/addons/purchase_force_invoiced/model/__init__.py
odoo/addons/purchase_force_invoiced/model/purchase_order.py
odoo/addons/purchase_force_invoiced/model/purchase_order_line.py
odoo/addons/purchase_force_invoiced/readme/CONTRIBUTORS.md
odoo/addons/purchase_force_invoiced/readme/DESCRIPTION.md
odoo/addons/purchase_force_invoiced/readme/USAGE.md
odoo/addons/purchase_force_invoiced/reports/__init__.py
odoo/addons/purchase_force_invoiced/reports/purchase_report.py
odoo/addons/purchase_force_invoiced/security/res_groups_data.xml
odoo/addons/purchase_force_invoiced/static/description/icon.png
odoo/addons/purchase_force_invoiced/static/description/index.html
odoo/addons/purchase_force_invoiced/tests/__init__.py
odoo/addons/purchase_force_invoiced/tests/test_purchase_force_invoiced.py
odoo/addons/purchase_force_invoiced/view/purchase_order.xml
odoo_addon_purchase_force_invoiced-18.0.1.0.1.5.dist-info/METADATA
odoo_addon_purchase_force_invoiced-18.0.1.0.1.5.dist-info/WHEEL
odoo_addon_purchase_force_invoiced-18.0.1.0.1.5.dist-info/top_level.txt
odoo_addon_purchase_force_invoiced-18.0.1.0.1.5.dist-info/RECORD
