Metadata-Version: 2.1
Name: odoo-addon-purchase_force_invoiced
Version: 18.0.1.0.1.5
Requires-Python: >=3.10
Requires-Dist: odoo==18.0.*
Summary: Allows to force the billing status of the purchase order to "Invoiced"
Home-page: https://github.com/OCA/purchase-workflow
License: AGPL-3
Author: Forgeflow, Odoo Community Association (OCA)
Author-email: support@odoo-community.org
Classifier: Programming Language :: Python
Classifier: Framework :: Odoo
Classifier: Framework :: Odoo :: 18.0
Classifier: License :: OSI Approved :: GNU Affero General Public License v3
